emailahoy3
