Metadata-Version: 2.1
Name: python-emailahoy3
Version: 0.1.2
Summary: A Python3 email utility that verifies existence of an email address
Home-page: https://github.com/febrezo/python-emailahoy3
Author: Val Neekman and Félix Brezo
Author-email: felix.brezo@i3visio.com
License: BSD
Platform: UNKNOWN
Classifier: Development Status :: 3 - Alpha
Classifier: Intended Audience :: Developers
Classifier: License :: OSI Approved :: BSD License
Classifier: Operating System :: POSIX
Classifier: Programming Language :: Python
Classifier: Topic :: Software Development :: Libraries :: Python Modules
Classifier: Topic :: Communications :: Email
